[
  {
    "solver": "temporis",
    "game": "test001",
    "status": "success",
    "time": 6.000000000000001e-08,
    "output": "0.000060",
    "timestamp": 1760528853.0185347,
    "vertices": 10,
    "time_bound": 5
  },
  {
    "solver": "ontime",
    "game": "test001",
    "status": "success",
    "time": 0.003055572509765625,
    "output": "W_5 = {\"v3\"}\nW_0 = {\"v9\", \"v3\", \"v4\", \"v0\"}",
    "timestamp": 1760528853.021695,
    "vertices": 10,
    "time_bound": 5
  },
  {
    "solver": "temporis",
    "game": "test002",
    "status": "success",
    "time": 4.6e-08,
    "output": "0.000046",
    "timestamp": 1760528853.0237775,
    "vertices": 10,
    "time_bound": 10
  },
  {
    "solver": "ontime",
    "game": "test002",
    "status": "success",
    "time": 0.003108978271484375,
    "output": "W_10 = {\"v2\"}\nW_0 = {}",
    "timestamp": 1760528853.0269961,
    "vertices": 10,
    "time_bound": 10
  },
  {
    "solver": "temporis",
    "game": "test003",
    "status": "success",
    "time": 3.4999999999999996e-08,
    "output": "0.000035",
    "timestamp": 1760528853.028882,
    "vertices": 10,
    "time_bound": 8
  },
  {
    "solver": "ontime",
    "game": "test003",
    "status": "success",
    "time": 0.0035631656646728516,
    "output": "W_8 = {\"v7\"}\nW_0 = {}",
    "timestamp": 1760528853.0325437,
    "vertices": 10,
    "time_bound": 8
  },
  {
    "solver": "temporis",
    "game": "test004",
    "status": "success",
    "time": 4.2e-08,
    "output": "0.000042",
    "timestamp": 1760528853.0345664,
    "vertices": 10,
    "time_bound": 5
  },
  {
    "solver": "ontime",
    "game": "test004",
    "status": "success",
    "time": 0.002585172653198242,
    "output": "W_5 = {\"v0\"}\nW_0 = {\"v3\", \"v1\", \"v2\", \"v4\"}",
    "timestamp": 1760528853.0372534,
    "vertices": 10,
    "time_bound": 5
  },
  {
    "solver": "temporis",
    "game": "test005",
    "status": "success",
    "time": 8.6e-08,
    "output": "0.000086",
    "timestamp": 1760528853.0398004,
    "vertices": 10,
    "time_bound": 8
  },
  {
    "solver": "ontime",
    "game": "test005",
    "status": "success",
    "time": 0.0035254955291748047,
    "output": "W_8 = {\"v1\"}\nW_0 = {}",
    "timestamp": 1760528853.0434256,
    "vertices": 10,
    "time_bound": 8
  },
  {
    "solver": "temporis",
    "game": "test006",
    "status": "success",
    "time": 5.8e-08,
    "output": "0.000058",
    "timestamp": 1760528853.0454504,
    "vertices": 10,
    "time_bound": 10
  },
  {
    "solver": "ontime",
    "game": "test006",
    "status": "success",
    "time": 0.0037009716033935547,
    "output": "W_10 = {\"v5\"}\nW_0 = {\"v7\"}",
    "timestamp": 1760528853.0492752,
    "vertices": 10,
    "time_bound": 10
  },
  {
    "solver": "temporis",
    "game": "test007",
    "status": "success",
    "time": 4.2e-08,
    "output": "0.000042",
    "timestamp": 1760528853.0511775,
    "vertices": 10,
    "time_bound": 8
  },
  {
    "solver": "ontime",
    "game": "test007",
    "status": "success",
    "time": 0.002917051315307617,
    "output": "W_8 = {\"v8\"}\nW_0 = {}",
    "timestamp": 1760528853.0542073,
    "vertices": 10,
    "time_bound": 8
  },
  {
    "solver": "temporis",
    "game": "test008",
    "status": "success",
    "time": 4.7e-08,
    "output": "0.000047",
    "timestamp": 1760528853.0562625,
    "vertices": 10,
    "time_bound": 5
  },
  {
    "solver": "ontime",
    "game": "test008",
    "status": "success",
    "time": 0.003341197967529297,
    "output": "W_5 = {\"v5\"}\nW_0 = {}",
    "timestamp": 1760528853.0597174,
    "vertices": 10,
    "time_bound": 5
  },
  {
    "solver": "temporis",
    "game": "test009",
    "status": "success",
    "time": 6.3e-08,
    "output": "0.000063",
    "timestamp": 1760528853.061609,
    "vertices": 10,
    "time_bound": 9
  },
  {
    "solver": "ontime",
    "game": "test009",
    "status": "success",
    "time": 0.003122568130493164,
    "output": "W_9 = {\"v5\"}\nW_0 = {}",
    "timestamp": 1760528853.06483,
    "vertices": 10,
    "time_bound": 9
  },
  {
    "solver": "temporis",
    "game": "test010",
    "status": "success",
    "time": 4.6e-08,
    "output": "0.000046",
    "timestamp": 1760528853.0666683,
    "vertices": 10,
    "time_bound": 5
  },
  {
    "solver": "ontime",
    "game": "test010",
    "status": "success",
    "time": 0.0027625560760498047,
    "output": "W_5 = {\"v6\"}\nW_0 = {}",
    "timestamp": 1760528853.0695176,
    "vertices": 10,
    "time_bound": 5
  },
  {
    "solver": "temporis",
    "game": "test011",
    "status": "success",
    "time": 6.1e-08,
    "output": "0.000061",
    "timestamp": 1760528853.0714817,
    "vertices": 10,
    "time_bound": 8
  },
  {
    "solver": "ontime",
    "game": "test011",
    "status": "success",
    "time": 0.004035472869873047,
    "output": "W_8 = {\"v5\"}\nW_0 = {}",
    "timestamp": 1760528853.075606,
    "vertices": 10,
    "time_bound": 8
  },
  {
    "solver": "temporis",
    "game": "test012",
    "status": "success",
    "time": 4.6e-08,
    "output": "0.000046",
    "timestamp": 1760528853.0774972,
    "vertices": 10,
    "time_bound": 9
  },
  {
    "solver": "ontime",
    "game": "test012",
    "status": "success",
    "time": 0.0031328201293945312,
    "output": "W_9 = {\"v2\"}\nW_0 = {}",
    "timestamp": 1760528853.0806978,
    "vertices": 10,
    "time_bound": 9
  },
  {
    "solver": "temporis",
    "game": "test013",
    "status": "success",
    "time": 4.5000000000000006e-08,
    "output": "0.000045",
    "timestamp": 1760528853.0823905,
    "vertices": 10,
    "time_bound": 8
  },
  {
    "solver": "ontime",
    "game": "test013",
    "status": "success",
    "time": 0.003160715103149414,
    "output": "W_8 = {\"v0\"}\nW_0 = {}",
    "timestamp": 1760528853.0856507,
    "vertices": 10,
    "time_bound": 8
  },
  {
    "solver": "temporis",
    "game": "test014",
    "status": "success",
    "time": 6.600000000000001e-08,
    "output": "0.000066",
    "timestamp": 1760528853.087635,
    "vertices": 10,
    "time_bound": 10
  },
  {
    "solver": "ontime",
    "game": "test014",
    "status": "success",
    "time": 0.004595518112182617,
    "output": "W_10 = {\"v1\"}\nW_0 = {}",
    "timestamp": 1760528853.092326,
    "vertices": 10,
    "time_bound": 10
  },
  {
    "solver": "temporis",
    "game": "test015",
    "status": "success",
    "time": 6.399999999999999e-08,
    "output": "0.000064",
    "timestamp": 1760528853.0942316,
    "vertices": 10,
    "time_bound": 8
  },
  {
    "solver": "ontime",
    "game": "test015",
    "status": "success",
    "time": 0.003462076187133789,
    "output": "W_8 = {\"v5\"}\nW_0 = {\"v4\", \"v9\", \"v5\"}",
    "timestamp": 1760528853.097795,
    "vertices": 10,
    "time_bound": 8
  },
  {
    "solver": "temporis",
    "game": "test016",
    "status": "success",
    "time": 1.43e-07,
    "output": "0.000143",
    "timestamp": 1760528853.1001344,
    "vertices": 20,
    "time_bound": 8
  },
  {
    "solver": "ontime",
    "game": "test016",
    "status": "success",
    "time": 0.006036043167114258,
    "output": "W_8 = {\"v2\", \"v13\", \"v11\"}\nW_0 = {\"v9\", \"v10\", \"v1\", \"v8\", \"v16\"}",
    "timestamp": 1760528853.1062615,
    "vertices": 20,
    "time_bound": 8
  },
  {
    "solver": "temporis",
    "game": "test017",
    "status": "success",
    "time": 1.67e-07,
    "output": "0.000167",
    "timestamp": 1760528853.1086316,
    "vertices": 20,
    "time_bound": 7
  },
  {
    "solver": "ontime",
    "game": "test017",
    "status": "success",
    "time": 0.0054247379302978516,
    "output": "W_7 = {\"v7\", \"v0\", \"v16\"}\nW_0 = {}",
    "timestamp": 1760528853.1141622,
    "vertices": 20,
    "time_bound": 7
  },
  {
    "solver": "temporis",
    "game": "test018",
    "status": "success",
    "time": 1.12e-07,
    "output": "0.000112",
    "timestamp": 1760528853.1163087,
    "vertices": 20,
    "time_bound": 10
  },
  {
    "solver": "ontime",
    "game": "test018",
    "status": "success",
    "time": 0.005183696746826172,
    "output": "W_10 = {\"v2\", \"v5\", \"v16\"}\nW_0 = {}",
    "timestamp": 1760528853.1215756,
    "vertices": 20,
    "time_bound": 10
  },
  {
    "solver": "temporis",
    "game": "test019",
    "status": "success",
    "time": 1.15e-07,
    "output": "0.000115",
    "timestamp": 1760528853.1238775,
    "vertices": 20,
    "time_bound": 9
  },
  {
    "solver": "ontime",
    "game": "test019",
    "status": "success",
    "time": 0.0049741268157958984,
    "output": "W_9 = {\"v10\", \"v17\", \"v14\"}\nW_0 = {}",
    "timestamp": 1760528853.1289675,
    "vertices": 20,
    "time_bound": 9
  },
  {
    "solver": "temporis",
    "game": "test020",
    "status": "success",
    "time": 1.2000000000000002e-07,
    "output": "0.000120",
    "timestamp": 1760528853.1311102,
    "vertices": 20,
    "time_bound": 6
  },
  {
    "solver": "ontime",
    "game": "test020",
    "status": "success",
    "time": 0.005195140838623047,
    "output": "W_6 = {\"v8\", \"v12\", \"v0\"}\nW_0 = {}",
    "timestamp": 1760528853.1363716,
    "vertices": 20,
    "time_bound": 6
  },
  {
    "solver": "temporis",
    "game": "test021",
    "status": "success",
    "time": 1.16e-07,
    "output": "0.000116",
    "timestamp": 1760528853.1385484,
    "vertices": 20,
    "time_bound": 6
  },
  {
    "solver": "ontime",
    "game": "test021",
    "status": "success",
    "time": 0.0050508975982666016,
    "output": "W_6 = {\"v19\", \"v17\"}\nW_0 = {}",
    "timestamp": 1760528853.1437123,
    "vertices": 20,
    "time_bound": 6
  },
  {
    "solver": "temporis",
    "game": "test022",
    "status": "success",
    "time": 9.4e-08,
    "output": "0.000094",
    "timestamp": 1760528853.1457438,
    "vertices": 20,
    "time_bound": 8
  },
  {
    "solver": "ontime",
    "game": "test022",
    "status": "success",
    "time": 0.0041408538818359375,
    "output": "W_8 = {\"v4\", \"v13\"}\nW_0 = {}",
    "timestamp": 1760528853.149961,
    "vertices": 20,
    "time_bound": 8
  },
  {
    "solver": "temporis",
    "game": "test023",
    "status": "success",
    "time": 1.39e-07,
    "output": "0.000139",
    "timestamp": 1760528853.1522858,
    "vertices": 20,
    "time_bound": 6
  },
  {
    "solver": "ontime",
    "game": "test023",
    "status": "success",
    "time": 0.005819797515869141,
    "output": "W_6 = {\"v9\", \"v5\", \"v19\"}\nW_0 = {}",
    "timestamp": 1760528853.1582067,
    "vertices": 20,
    "time_bound": 6
  },
  {
    "solver": "temporis",
    "game": "test024",
    "status": "success",
    "time": 1.0900000000000001e-07,
    "output": "0.000109",
    "timestamp": 1760528853.160534,
    "vertices": 20,
    "time_bound": 10
  },
  {
    "solver": "ontime",
    "game": "test024",
    "status": "success",
    "time": 0.005184650421142578,
    "output": "W_10 = {\"v7\", \"v2\"}\nW_0 = {}",
    "timestamp": 1760528853.165833,
    "vertices": 20,
    "time_bound": 10
  },
  {
    "solver": "temporis",
    "game": "test025",
    "status": "success",
    "time": 1.2000000000000002e-07,
    "output": "0.000120",
    "timestamp": 1760528853.1679285,
    "vertices": 20,
    "time_bound": 10
  },
  {
    "solver": "ontime",
    "game": "test025",
    "status": "success",
    "time": 0.004262208938598633,
    "output": "W_10 = {\"v16\", \"v7\"}\nW_0 = {\"v18\", \"v9\", \"v1\", \"v4\", \"v2\", \"v7\"}",
    "timestamp": 1760528853.172281,
    "vertices": 20,
    "time_bound": 10
  },
  {
    "solver": "temporis",
    "game": "test026",
    "status": "success",
    "time": 7.7e-08,
    "output": "0.000077",
    "timestamp": 1760528853.174373,
    "vertices": 20,
    "time_bound": 5
  },
  {
    "solver": "ontime",
    "game": "test026",
    "status": "success",
    "time": 0.0037696361541748047,
    "output": "W_5 = {\"v7\", \"v19\"}\nW_0 = {}",
    "timestamp": 1760528853.1782537,
    "vertices": 20,
    "time_bound": 5
  },
  {
    "solver": "temporis",
    "game": "test027",
    "status": "success",
    "time": 8.6e-08,
    "output": "0.000086",
    "timestamp": 1760528853.1801903,
    "vertices": 20,
    "time_bound": 7
  },
  {
    "solver": "ontime",
    "game": "test027",
    "status": "success",
    "time": 0.003954887390136719,
    "output": "W_7 = {\"v15\", \"v17\"}\nW_0 = {\"v12\", \"v9\"}",
    "timestamp": 1760528853.1842167,
    "vertices": 20,
    "time_bound": 7
  },
  {
    "solver": "temporis",
    "game": "test028",
    "status": "success",
    "time": 1.0900000000000001e-07,
    "output": "0.000109",
    "timestamp": 1760528853.1864312,
    "vertices": 20,
    "time_bound": 10
  },
  {
    "solver": "ontime",
    "game": "test028",
    "status": "success",
    "time": 0.0060880184173583984,
    "output": "W_10 = {\"v1\", \"v11\", \"v16\"}\nW_0 = {}",
    "timestamp": 1760528853.1926105,
    "vertices": 20,
    "time_bound": 10
  },
  {
    "solver": "temporis",
    "game": "test029",
    "status": "success",
    "time": 1.54e-07,
    "output": "0.000154",
    "timestamp": 1760528853.194866,
    "vertices": 20,
    "time_bound": 10
  },
  {
    "solver": "ontime",
    "game": "test029",
    "status": "success",
    "time": 0.005173683166503906,
    "output": "W_10 = {\"v1\", \"v0\", \"v12\"}\nW_0 = {\"v17\", \"v11\", \"v4\", \"v7\"}",
    "timestamp": 1760528853.2001164,
    "vertices": 20,
    "time_bound": 10
  },
  {
    "solver": "temporis",
    "game": "test030",
    "status": "success",
    "time": 1.2699999999999999e-07,
    "output": "0.000127",
    "timestamp": 1760528853.2022686,
    "vertices": 20,
    "time_bound": 10
  },
  {
    "solver": "ontime",
    "game": "test030",
    "status": "success",
    "time": 0.005864143371582031,
    "output": "W_10 = {\"v7\", \"v17\"}\nW_0 = {}",
    "timestamp": 1760528853.20821,
    "vertices": 20,
    "time_bound": 10
  },
  {
    "solver": "temporis",
    "game": "test031",
    "status": "success",
    "time": 2.09e-07,
    "output": "0.000209",
    "timestamp": 1760528853.2106657,
    "vertices": 30,
    "time_bound": 7
  },
  {
    "solver": "ontime",
    "game": "test031",
    "status": "success",
    "time": 0.006066560745239258,
    "output": "W_7 = {\"v2\", \"v5\", \"v25\", \"v16\", \"v13\"}\nW_0 = {\"v21\", \"v9\", \"v10\", \"v14\", \"v17\", \"v0\", \"v1\", \"v28\", \"v29\", \"v16\"}",
    "timestamp": 1760528853.2168312,
    "vertices": 30,
    "time_bound": 7
  },
  {
    "solver": "temporis",
    "game": "test032",
    "status": "success",
    "time": 2.33e-07,
    "output": "0.000233",
    "timestamp": 1760528853.2192972,
    "vertices": 30,
    "time_bound": 5
  },
  {
    "solver": "ontime",
    "game": "test032",
    "status": "success",
    "time": 0.006390094757080078,
    "output": "W_5 = {\"v12\", \"v25\", \"v29\", \"v16\", \"v11\"}\nW_0 = {\"v10\", \"v6\", \"v18\"}",
    "timestamp": 1760528853.2258112,
    "vertices": 30,
    "time_bound": 5
  },
  {
    "solver": "temporis",
    "game": "test033",
    "status": "success",
    "time": 1.3999999999999998e-07,
    "output": "0.000140",
    "timestamp": 1760528853.2282069,
    "vertices": 30,
    "time_bound": 8
  },
  {
    "solver": "ontime",
    "game": "test033",
    "status": "success",
    "time": 0.0054607391357421875,
    "output": "W_8 = {\"v29\", \"v11\", \"v18\", \"v17\", \"v26\"}\nW_0 = {\"v18\"}",
    "timestamp": 1760528853.2337663,
    "vertices": 30,
    "time_bound": 8
  },
  {
    "solver": "temporis",
    "game": "test034",
    "status": "success",
    "time": 1.93e-07,
    "output": "0.000193",
    "timestamp": 1760528853.2362611,
    "vertices": 30,
    "time_bound": 5
  },
  {
    "solver": "ontime",
    "game": "test034",
    "status": "success",
    "time": 0.007439136505126953,
    "output": "W_5 = {\"v3\", \"v2\", \"v29\"}\nW_0 = {}",
    "timestamp": 1760528853.2437832,
    "vertices": 30,
    "time_bound": 5
  },
  {
    "solver": "temporis",
    "game": "test035",
    "status": "success",
    "time": 2.3e-07,
    "output": "0.000230",
    "timestamp": 1760528853.2463696,
    "vertices": 30,
    "time_bound": 10
  },
  {
    "solver": "ontime",
    "game": "test035",
    "status": "success",
    "time": 0.006551265716552734,
    "output": "W_10 = {\"v6\", \"v7\", \"v16\", \"v21\"}\nW_0 = {\"v17\", \"v3\", \"v12\", \"v1\"}",
    "timestamp": 1760528853.2530334,
    "vertices": 30,
    "time_bound": 10
  },
  {
    "solver": "temporis",
    "game": "test036",
    "status": "success",
    "time": 2.12e-07,
    "output": "0.000212",
    "timestamp": 1760528853.2558072,
    "vertices": 30,
    "time_bound": 8
  },
  {
    "solver": "ontime",
    "game": "test036",
    "status": "success",
    "time": 0.007971525192260742,
    "output": "W_8 = {\"v0\", \"v12\", \"v28\", \"v26\"}\nW_0 = {}",
    "timestamp": 1760528853.2639086,
    "vertices": 30,
    "time_bound": 8
  },
  {
    "solver": "temporis",
    "game": "test037",
    "status": "success",
    "time": 1.11e-07,
    "output": "0.000111",
    "timestamp": 1760528853.266046,
    "vertices": 30,
    "time_bound": 8
  },
  {
    "solver": "ontime",
    "game": "test037",
    "status": "success",
    "time": 0.0048525333404541016,
    "output": "W_8 = {\"v29\", \"v23\", \"v13\", \"v26\"}\nW_0 = {}",
    "timestamp": 1760528853.270989,
    "vertices": 30,
    "time_bound": 8
  },
  {
    "solver": "temporis",
    "game": "test038",
    "status": "success",
    "time": 2.1900000000000002e-07,
    "output": "0.000219",
    "timestamp": 1760528853.273504,
    "vertices": 30,
    "time_bound": 7
  },
  {
    "solver": "ontime",
    "game": "test038",
    "status": "success",
    "time": 0.005416393280029297,
    "output": "W_7 = {\"v26\", \"v12\", \"v22\", \"v25\"}\nW_0 = {}",
    "timestamp": 1760528853.2790484,
    "vertices": 30,
    "time_bound": 7
  },
  {
    "solver": "temporis",
    "game": "test039",
    "status": "success",
    "time": 2.3800000000000001e-07,
    "output": "0.000238",
    "timestamp": 1760528853.2818692,
    "vertices": 30,
    "time_bound": 10
  },
  {
    "solver": "ontime",
    "game": "test039",
    "status": "success",
    "time": 0.007299900054931641,
    "output": "W_10 = {\"v2\", \"v27\", \"v16\"}\nW_0 = {}",
    "timestamp": 1760528853.2892795,
    "vertices": 30,
    "time_bound": 10
  },
  {
    "solver": "temporis",
    "game": "test040",
    "status": "success",
    "time": 1.07e-07,
    "output": "0.000107",
    "timestamp": 1760528853.2918398,
    "vertices": 30,
    "time_bound": 8
  },
  {
    "solver": "ontime",
    "game": "test040",
    "status": "success",
    "time": 0.004389286041259766,
    "output": "W_8 = {\"v14\", \"v18\", \"v29\", \"v7\"}\nW_0 = {}",
    "timestamp": 1760528853.2963362,
    "vertices": 30,
    "time_bound": 8
  },
  {
    "solver": "temporis",
    "game": "test041",
    "status": "success",
    "time": 2.72e-07,
    "output": "0.000272",
    "timestamp": 1760528853.2991672,
    "vertices": 30,
    "time_bound": 8
  },
  {
    "solver": "ontime",
    "game": "test041",
    "status": "success",
    "time": 0.009563207626342773,
    "output": "W_8 = {\"v9\", \"v20\", \"v7\"}\nW_0 = {}",
    "timestamp": 1760528853.3088124,
    "vertices": 30,
    "time_bound": 8
  },
  {
    "solver": "temporis",
    "game": "test042",
    "status": "success",
    "time": 1.33e-07,
    "output": "0.000133",
    "timestamp": 1760528853.3110168,
    "vertices": 30,
    "time_bound": 8
  },
  {
    "solver": "ontime",
    "game": "test042",
    "status": "success",
    "time": 0.0056498050689697266,
    "output": "W_8 = {\"v5\", \"v29\", \"v6\", \"v3\"}\nW_0 = {\"v12\", \"v3\", \"v25\", \"v26\", \"v29\"}",
    "timestamp": 1760528853.3167431,
    "vertices": 30,
    "time_bound": 8
  },
  {
    "solver": "temporis",
    "game": "test043",
    "status": "success",
    "time": 2.01e-07,
    "output": "0.000201",
    "timestamp": 1760528853.3193033,
    "vertices": 30,
    "time_bound": 7
  },
  {
    "solver": "ontime",
    "game": "test043",
    "status": "success",
    "time": 0.006971597671508789,
    "output": "W_7 = {\"v17\", \"v27\", \"v10\", \"v25\"}\nW_0 = {}",
    "timestamp": 1760528853.3263743,
    "vertices": 30,
    "time_bound": 7
  },
  {
    "solver": "temporis",
    "game": "test044",
    "status": "success",
    "time": 1.91e-07,
    "output": "0.000191",
    "timestamp": 1760528853.3292515,
    "vertices": 30,
    "time_bound": 7
  },
  {
    "solver": "ontime",
    "game": "test044",
    "status": "success",
    "time": 0.007773399353027344,
    "output": "W_7 = {\"v8\", \"v2\", \"v9\", \"v29\", \"v12\"}\nW_0 = {}",
    "timestamp": 1760528853.3371131,
    "vertices": 30,
    "time_bound": 7
  },
  {
    "solver": "temporis",
    "game": "test045",
    "status": "success",
    "time": 1.2799999999999998e-07,
    "output": "0.000128",
    "timestamp": 1760528853.3394988,
    "vertices": 30,
    "time_bound": 6
  },
  {
    "solver": "ontime",
    "game": "test045",
    "status": "success",
    "time": 0.005542278289794922,
    "output": "W_6 = {\"v25\", \"v15\", \"v9\", \"v29\"}\nW_0 = {\"v25\", \"v7\", \"v14\"}",
    "timestamp": 1760528853.3451705,
    "vertices": 30,
    "time_bound": 6
  },
  {
    "solver": "temporis",
    "game": "test046",
    "status": "success",
    "time": 1.98e-07,
    "output": "0.000198",
    "timestamp": 1760528853.3477936,
    "vertices": 40,
    "time_bound": 10
  },
  {
    "solver": "ontime",
    "game": "test046",
    "status": "success",
    "time": 0.007297992706298828,
    "output": "W_10 = {\"v35\", \"v7\", \"v6\", \"v32\", \"v37\", \"v38\", \"v2\"}\nW_0 = {}",
    "timestamp": 1760528853.3551815,
    "vertices": 40,
    "time_bound": 10
  },
  {
    "solver": "temporis",
    "game": "test047",
    "status": "success",
    "time": 1.9599999999999998e-07,
    "output": "0.000196",
    "timestamp": 1760528853.3579695,
    "vertices": 40,
    "time_bound": 8
  },
  {
    "solver": "ontime",
    "game": "test047",
    "status": "success",
    "time": 0.006829738616943359,
    "output": "W_8 = {\"v3\", \"v11\", \"v20\", \"v1\"}\nW_0 = {}",
    "timestamp": 1760528853.3649242,
    "vertices": 40,
    "time_bound": 8
  },
  {
    "solver": "temporis",
    "game": "test048",
    "status": "success",
    "time": 2.44e-07,
    "output": "0.000244",
    "timestamp": 1760528853.3678122,
    "vertices": 40,
    "time_bound": 7
  },
  {
    "solver": "ontime",
    "game": "test048",
    "status": "success",
    "time": 0.008581161499023438,
    "output": "W_7 = {\"v2\", \"v0\", \"v31\", \"v14\"}\nW_0 = {\"v26\", \"v7\"}",
    "timestamp": 1760528853.3764932,
    "vertices": 40,
    "time_bound": 7
  },
  {
    "solver": "temporis",
    "game": "test049",
    "status": "success",
    "time": 1.7000000000000001e-07,
    "output": "0.000170",
    "timestamp": 1760528853.3789587,
    "vertices": 40,
    "time_bound": 9
  },
  {
    "solver": "ontime",
    "game": "test049",
    "status": "success",
    "time": 0.006238698959350586,
    "output": "W_9 = {\"v24\", \"v3\", \"v19\", \"v28\", \"v33\", \"v0\", \"v6\"}\nW_0 = {}",
    "timestamp": 1760528853.3852873,
    "vertices": 40,
    "time_bound": 9
  },
  {
    "solver": "temporis",
    "game": "test050",
    "status": "success",
    "time": 1.67e-07,
    "output": "0.000167",
    "timestamp": 1760528853.3877532,
    "vertices": 40,
    "time_bound": 8
  },
  {
    "solver": "ontime",
    "game": "test050",
    "status": "success",
    "time": 0.006784677505493164,
    "output": "W_8 = {\"v24\", \"v5\", \"v26\", \"v37\", \"v34\", \"v19\"}\nW_0 = {}",
    "timestamp": 1760528853.3946517,
    "vertices": 40,
    "time_bound": 8
  },
  {
    "solver": "temporis",
    "game": "test051",
    "status": "success",
    "time": 2.5399999999999997e-07,
    "output": "0.000254",
    "timestamp": 1760528853.3975222,
    "vertices": 40,
    "time_bound": 8
  },
  {
    "solver": "ontime",
    "game": "test051",
    "status": "success",
    "time": 0.008428812026977539,
    "output": "W_8 = {\"v9\", \"v27\", \"v36\", \"v6\", \"v24\"}\nW_0 = {\"v25\"}",
    "timestamp": 1760528853.4060495,
    "vertices": 40,
    "time_bound": 8
  },
  {
    "solver": "temporis",
    "game": "test052",
    "status": "success",
    "time": 2.5399999999999997e-07,
    "output": "0.000254",
    "timestamp": 1760528853.4090369,
    "vertices": 40,
    "time_bound": 10
  },
  {
    "solver": "ontime",
    "game": "test052",
    "status": "success",
    "time": 0.0076024532318115234,
    "output": "W_10 = {\"v9\", \"v1\", \"v12\", \"v27\"}\nW_0 = {\"v24\"}",
    "timestamp": 1760528853.4167619,
    "vertices": 40,
    "time_bound": 10
  },
  {
    "solver": "temporis",
    "game": "test053",
    "status": "success",
    "time": 1.84e-07,
    "output": "0.000184",
    "timestamp": 1760528853.4193878,
    "vertices": 40,
    "time_bound": 10
  },
  {
    "solver": "ontime",
    "game": "test053",
    "status": "success",
    "time": 0.007177114486694336,
    "output": "W_10 = {\"v26\", \"v36\", \"v0\", \"v4\"}\nW_0 = {}",
    "timestamp": 1760528853.4266899,
    "vertices": 40,
    "time_bound": 10
  },
  {
    "solver": "temporis",
    "game": "test054",
    "status": "success",
    "time": 3.51e-07,
    "output": "0.000351",
    "timestamp": 1760528853.4297483,
    "vertices": 40,
    "time_bound": 9
  },
  {
    "solver": "ontime",
    "game": "test054",
    "status": "success",
    "time": 0.009311914443969727,
    "output": "W_9 = {\"v26\", \"v0\", \"v33\", \"v16\"}\nW_0 = {}",
    "timestamp": 1760528853.4391496,
    "vertices": 40,
    "time_bound": 9
  },
  {
    "solver": "temporis",
    "game": "test055",
    "status": "success",
    "time": 1.62e-07,
    "output": "0.000162",
    "timestamp": 1760528853.441638,
    "vertices": 40,
    "time_bound": 9
  },
  {
    "solver": "ontime",
    "game": "test055",
    "status": "success",
    "time": 0.0058896541595458984,
    "output": "W_9 = {\"v23\", \"v21\", \"v17\", \"v28\", \"v3\", \"v32\"}\nW_0 = {}",
    "timestamp": 1760528853.4476357,
    "vertices": 40,
    "time_bound": 9
  },
  {
    "solver": "temporis",
    "game": "test056",
    "status": "success",
    "time": 2.14e-07,
    "output": "0.000214",
    "timestamp": 1760528853.4504929,
    "vertices": 40,
    "time_bound": 7
  },
  {
    "solver": "ontime",
    "game": "test056",
    "status": "success",
    "time": 0.008447885513305664,
    "output": "W_7 = {\"v13\", \"v3\", \"v38\", \"v7\", \"v21\", \"v32\"}\nW_0 = {\"v15\"}",
    "timestamp": 1760528853.45904,
    "vertices": 40,
    "time_bound": 7
  },
  {
    "solver": "temporis",
    "game": "test057",
    "status": "success",
    "time": 2.2699999999999998e-07,
    "output": "0.000227",
    "timestamp": 1760528853.4617715,
    "vertices": 40,
    "time_bound": 8
  },
  {
    "solver": "ontime",
    "game": "test057",
    "status": "success",
    "time": 0.007282733917236328,
    "output": "W_8 = {\"v11\", \"v27\", \"v13\", \"v24\"}\nW_0 = {}",
    "timestamp": 1760528853.4691389,
    "vertices": 40,
    "time_bound": 8
  },
  {
    "solver": "temporis",
    "game": "test058",
    "status": "success",
    "time": 2.92e-07,
    "output": "0.000292",
    "timestamp": 1760528853.4725614,
    "vertices": 40,
    "time_bound": 7
  },
  {
    "solver": "ontime",
    "game": "test058",
    "status": "success",
    "time": 0.009431123733520508,
    "output": "W_7 = {\"v9\", \"v12\", \"v30\", \"v11\", \"v14\", \"v16\", \"v31\"}\nW_0 = {\"v38\"}",
    "timestamp": 1760528853.4821029,
    "vertices": 40,
    "time_bound": 7
  },
  {
    "solver": "temporis",
    "game": "test059",
    "status": "success",
    "time": 2.22e-07,
    "output": "0.000222",
    "timestamp": 1760528853.4846914,
    "vertices": 40,
    "time_bound": 9
  },
  {
    "solver": "ontime",
    "game": "test059",
    "status": "success",
    "time": 0.00727391242980957,
    "output": "W_9 = {\"v9\", \"v8\", \"v5\", \"v11\", \"v39\"}\nW_0 = {}",
    "timestamp": 1760528853.492043,
    "vertices": 40,
    "time_bound": 9
  },
  {
    "solver": "temporis",
    "game": "test060",
    "status": "success",
    "time": 2.0000000000000002e-07,
    "output": "0.000200",
    "timestamp": 1760528853.4947226,
    "vertices": 40,
    "time_bound": 5
  },
  {
    "solver": "ontime",
    "game": "test060",
    "status": "success",
    "time": 0.00638890266418457,
    "output": "W_5 = {\"v15\", \"v11\", \"v39\", \"v5\", \"v25\", \"v34\"}\nW_0 = {}",
    "timestamp": 1760528853.5012012,
    "vertices": 40,
    "time_bound": 5
  },
  {
    "solver": "temporis",
    "game": "test061",
    "status": "success",
    "time": 3.32e-07,
    "output": "0.000332",
    "timestamp": 1760528853.5046217,
    "vertices": 50,
    "time_bound": 7
  },
  {
    "solver": "ontime",
    "game": "test061",
    "status": "success",
    "time": 0.011099815368652344,
    "output": "W_7 = {\"v19\", \"v18\", \"v28\", \"v43\", \"v45\", \"v30\", \"v9\"}\nW_0 = {\"v41\"}",
    "timestamp": 1760528853.5158303,
    "vertices": 50,
    "time_bound": 7
  },
  {
    "solver": "temporis",
    "game": "test062",
    "status": "success",
    "time": 1.9e-07,
    "output": "0.000190",
    "timestamp": 1760528853.5183196,
    "vertices": 50,
    "time_bound": 10
  },
  {
    "solver": "ontime",
    "game": "test062",
    "status": "success",
    "time": 0.007043123245239258,
    "output": "W_10 = {\"v40\", \"v29\", \"v28\", \"v30\", \"v8\", \"v38\", \"v7\", \"v34\", \"v26\"}\nW_0 = {}",
    "timestamp": 1760528853.5254543,
    "vertices": 50,
    "time_bound": 10
  },
  {
    "solver": "temporis",
    "game": "test063",
    "status": "success",
    "time": 3.3e-07,
    "output": "0.000330",
    "timestamp": 1760528853.528573,
    "vertices": 50,
    "time_bound": 6
  },
  {
    "solver": "ontime",
    "game": "test063",
    "status": "success",
    "time": 0.010166406631469727,
    "output": "W_6 = {\"v39\", \"v21\", \"v31\", \"v11\", \"v49\", \"v22\", \"v5\", \"v48\"}\nW_0 = {}",
    "timestamp": 1760528853.5388298,
    "vertices": 50,
    "time_bound": 6
  },
  {
    "solver": "temporis",
    "game": "test064",
    "status": "success",
    "time": 2.8699999999999996e-07,
    "output": "0.000287",
    "timestamp": 1760528853.5420103,
    "vertices": 50,
    "time_bound": 6
  },
  {
    "solver": "ontime",
    "game": "test064",
    "status": "success",
    "time": 0.00985860824584961,
    "output": "W_6 = {\"v41\", \"v22\", \"v29\", \"v24\", \"v25\", \"v3\", \"v12\", \"v9\", \"v18\"}\nW_0 = {}",
    "timestamp": 1760528853.5519738,
    "vertices": 50,
    "time_bound": 6
  },
  {
    "solver": "temporis",
    "game": "test065",
    "status": "success",
    "time": 2.63e-07,
    "output": "0.000263",
    "timestamp": 1760528853.554721,
    "vertices": 50,
    "time_bound": 10
  },
  {
    "solver": "ontime",
    "game": "test065",
    "status": "success",
    "time": 0.008094072341918945,
    "output": "W_10 = {\"v13\", \"v48\", \"v11\", \"v42\", \"v1\", \"v9\", \"v6\", \"v37\"}\nW_0 = {\"v37\", \"v49\", \"v2\"}",
    "timestamp": 1760528853.56292,
    "vertices": 50,
    "time_bound": 10
  },
  {
    "solver": "temporis",
    "game": "test066",
    "status": "success",
    "time": 3.63e-07,
    "output": "0.000363",
    "timestamp": 1760528853.566405,
    "vertices": 50,
    "time_bound": 9
  },
  {
    "solver": "ontime",
    "game": "test066",
    "status": "success",
    "time": 0.009649038314819336,
    "output": "W_9 = {\"v35\", \"v9\", \"v23\", \"v46\", \"v49\", \"v42\", \"v34\"}\nW_0 = {}",
    "timestamp": 1760528853.5761654,
    "vertices": 50,
    "time_bound": 9
  },
  {
    "solver": "temporis",
    "game": "test067",
    "status": "success",
    "time": 3.75e-07,
    "output": "0.000375",
    "timestamp": 1760528853.579641,
    "vertices": 50,
    "time_bound": 5
  },
  {
    "solver": "ontime",
    "game": "test067",
    "status": "success",
    "time": 0.011455774307250977,
    "output": "W_5 = {\"v38\", \"v29\", \"v34\", \"v9\", \"v21\", \"v4\", \"v45\", \"v7\", \"v16\"}\nW_0 = {\"v35\"}",
    "timestamp": 1760528853.5911782,
    "vertices": 50,
    "time_bound": 5
  },
  {
    "solver": "temporis",
    "game": "test068",
    "status": "success",
    "time": 2.5399999999999997e-07,
    "output": "0.000254",
    "timestamp": 1760528853.5940351,
    "vertices": 50,
    "time_bound": 10
  },
  {
    "solver": "ontime",
    "game": "test068",
    "status": "success",
    "time": 0.008225202560424805,
    "output": "W_10 = {\"v4\", \"v9\", \"v8\", \"v46\", \"v28\"}\nW_0 = {}",
    "timestamp": 1760528853.602348,
    "vertices": 50,
    "time_bound": 10
  },
  {
    "solver": "temporis",
    "game": "test069",
    "status": "success",
    "time": 3.93e-07,
    "output": "0.000393",
    "timestamp": 1760528853.6059687,
    "vertices": 50,
    "time_bound": 9
  },
  {
    "solver": "ontime",
    "game": "test069",
    "status": "success",
    "time": 0.012045860290527344,
    "output": "W_9 = {\"v49\", \"v37\", \"v17\", \"v15\", \"v26\", \"v18\", \"v39\"}\nW_0 = {\"v11\", \"v4\", \"v0\", \"v44\", \"v13\"}",
    "timestamp": 1760528853.618162,
    "vertices": 50,
    "time_bound": 9
  },
  {
    "solver": "temporis",
    "game": "test070",
    "status": "success",
    "time": 2.9500000000000003e-07,
    "output": "0.000295",
    "timestamp": 1760528853.6212182,
    "vertices": 50,
    "time_bound": 10
  },
  {
    "solver": "ontime",
    "game": "test070",
    "status": "success",
    "time": 0.009501218795776367,
    "output": "W_10 = {\"v49\", \"v36\", \"v32\", \"v15\", \"v1\", \"v23\", \"v33\", \"v6\", \"v14\"}\nW_0 = {}",
    "timestamp": 1760528853.63081,
    "vertices": 50,
    "time_bound": 10
  },
  {
    "solver": "temporis",
    "game": "test071",
    "status": "success",
    "time": 2.4000000000000003e-07,
    "output": "0.000240",
    "timestamp": 1760528853.633593,
    "vertices": 50,
    "time_bound": 5
  },
  {
    "solver": "ontime",
    "game": "test071",
    "status": "success",
    "time": 0.008411407470703125,
    "output": "W_5 = {\"v16\", \"v12\", \"v4\", \"v34\", \"v43\", \"v33\"}\nW_0 = {}",
    "timestamp": 1760528853.6420908,
    "vertices": 50,
    "time_bound": 5
  },
  {
    "solver": "temporis",
    "game": "test072",
    "status": "success",
    "time": 2.6e-07,
    "output": "0.000260",
    "timestamp": 1760528853.644889,
    "vertices": 50,
    "time_bound": 6
  },
  {
    "solver": "ontime",
    "game": "test072",
    "status": "success",
    "time": 0.00792837142944336,
    "output": "W_6 = {\"v45\", \"v20\", \"v18\", \"v49\", \"v29\", \"v6\"}\nW_0 = {\"v37\"}",
    "timestamp": 1760528853.6529179,
    "vertices": 50,
    "time_bound": 6
  },
  {
    "solver": "temporis",
    "game": "test073",
    "status": "success",
    "time": 3.28e-07,
    "output": "0.000328",
    "timestamp": 1760528853.6563063,
    "vertices": 50,
    "time_bound": 9
  },
  {
    "solver": "ontime",
    "game": "test073",
    "status": "success",
    "time": 0.010852336883544922,
    "output": "W_9 = {\"v49\", \"v41\", \"v36\", \"v9\", \"v10\", \"v22\", \"v5\", \"v37\", \"v1\"}\nW_0 = {}",
    "timestamp": 1760528853.6672873,
    "vertices": 50,
    "time_bound": 9
  },
  {
    "solver": "temporis",
    "game": "test074",
    "status": "success",
    "time": 3.9199999999999996e-07,
    "output": "0.000392",
    "timestamp": 1760528853.6707616,
    "vertices": 50,
    "time_bound": 5
  },
  {
    "solver": "ontime",
    "game": "test074",
    "status": "success",
    "time": 0.011035442352294922,
    "output": "W_5 = {\"v48\", \"v14\", \"v21\", \"v35\", \"v24\", \"v22\", \"v6\", \"v44\"}\nW_0 = {\"v44\", \"v35\", \"v27\", \"v16\"}",
    "timestamp": 1760528853.6819034,
    "vertices": 50,
    "time_bound": 5
  },
  {
    "solver": "temporis",
    "game": "test075",
    "status": "success",
    "time": 1.97e-07,
    "output": "0.000197",
    "timestamp": 1760528853.6845613,
    "vertices": 50,
    "time_bound": 5
  },
  {
    "solver": "ontime",
    "game": "test075",
    "status": "success",
    "time": 0.007063388824462891,
    "output": "W_5 = {\"v1\", \"v7\", \"v0\", \"v14\", \"v11\"}\nW_0 = {}",
    "timestamp": 1760528853.691723,
    "vertices": 50,
    "time_bound": 5
  },
  {
    "solver": "temporis",
    "game": "test076",
    "status": "success",
    "time": 3.63e-07,
    "output": "0.000363",
    "timestamp": 1760528853.6951206,
    "vertices": 60,
    "time_bound": 9
  },
  {
    "solver": "ontime",
    "game": "test076",
    "status": "success",
    "time": 0.009099245071411133,
    "output": "W_9 = {\"v35\", \"v42\", \"v22\", \"v39\", \"v25\", \"v49\"}\nW_0 = {}",
    "timestamp": 1760528853.7043254,
    "vertices": 60,
    "time_bound": 9
  },
  {
    "solver": "temporis",
    "game": "test077",
    "status": "success",
    "time": 6.25e-07,
    "output": "0.000625",
    "timestamp": 1760528853.708634,
    "vertices": 60,
    "time_bound": 7
  },
  {
    "solver": "ontime",
    "game": "test077",
    "status": "success",
    "time": 0.01589512825012207,
    "output": "W_7 = {\"v8\", \"v7\", \"v4\", \"v46\", \"v33\", \"v57\", \"v55\", \"v47\", \"v26\"}\nW_0 = {\"v7\"}",
    "timestamp": 1760528853.7246764,
    "vertices": 60,
    "time_bound": 7
  },
  {
    "solver": "temporis",
    "game": "test078",
    "status": "success",
    "time": 6.42e-07,
    "output": "0.000642",
    "timestamp": 1760528853.728903,
    "vertices": 60,
    "time_bound": 8
  },
  {
    "solver": "ontime",
    "game": "test078",
    "status": "success",
    "time": 0.015124082565307617,
    "output": "W_8 = {\"v59\", \"v24\", \"v53\", \"v1\", \"v51\", \"v22\", \"v17\", \"v49\", \"v31\"}\nW_0 = {\"v42\", \"v57\", \"v59\", \"v30\", \"v46\", \"v6\", \"v29\", \"v2\", \"v41\", \"v55\"}",
    "timestamp": 1760528853.744156,
    "vertices": 60,
    "time_bound": 8
  },
  {
    "solver": "temporis",
    "game": "test079",
    "status": "success",
    "time": 6.1e-07,
    "output": "0.000610",
    "timestamp": 1760528853.7481093,
    "vertices": 60,
    "time_bound": 12
  },
  {
    "solver": "ontime",
    "game": "test079",
    "status": "success",
    "time": 0.013499021530151367,
    "output": "W_12 = {\"v34\", \"v7\", \"v2\", \"v58\", \"v50\", \"v39\", \"v16\", \"v10\", \"v13\", \"v18\"}\nW_0 = {\"v36\", \"v44\", \"v7\", \"v13\", \"v54\", \"v12\", \"v28\", \"v20\", \"v42\", \"v50\", \"v56\", \"v3\"}",
    "timestamp": 1760528853.7617083,
    "vertices": 60,
    "time_bound": 12
  },
  {
    "solver": "temporis",
    "game": "test080",
    "status": "success",
    "time": 3.88e-07,
    "output": "0.000388",
    "timestamp": 1760528853.76515,
    "vertices": 60,
    "time_bound": 9
  },
  {
    "solver": "ontime",
    "game": "test080",
    "status": "success",
    "time": 0.011004209518432617,
    "output": "W_9 = {\"v2\", \"v36\", \"v3\", \"v34\", \"v37\", \"v7\", \"v1\", \"v44\", \"v50\"}\nW_0 = {\"v7\", \"v48\"}",
    "timestamp": 1760528853.7762835,
    "vertices": 60,
    "time_bound": 9
  },
  {
    "solver": "temporis",
    "game": "test081",
    "status": "success",
    "time": 2.71e-07,
    "output": "0.000271",
    "timestamp": 1760528853.7792323,
    "vertices": 60,
    "time_bound": 6
  },
  {
    "solver": "ontime",
    "game": "test081",
    "status": "success",
    "time": 0.008960723876953125,
    "output": "W_6 = {\"v15\", \"v4\", \"v0\", \"v16\", \"v53\", \"v26\", \"v29\", \"v19\", \"v30\"}\nW_0 = {\"v26\", \"v15\", \"v35\"}",
    "timestamp": 1760528853.7883031,
    "vertices": 60,
    "time_bound": 6
  },
  {
    "solver": "temporis",
    "game": "test082",
    "status": "success",
    "time": 6.809999999999999e-07,
    "output": "0.000681",
    "timestamp": 1760528853.7925017,
    "vertices": 60,
    "time_bound": 7
  },
  {
    "solver": "ontime",
    "game": "test082",
    "status": "success",
    "time": 0.014473438262939453,
    "output": "W_7 = {\"v47\", \"v23\", \"v0\", \"v51\", \"v40\", \"v46\", \"v31\"}\nW_0 = {\"v55\", \"v30\", \"v54\", \"v11\", \"v43\", \"v29\", \"v51\", \"v44\", \"v32\", \"v56\", \"v41\", \"v47\"}",
    "timestamp": 1760528853.8070948,
    "vertices": 60,
    "time_bound": 7
  },
  {
    "solver": "temporis",
    "game": "test083",
    "status": "success",
    "time": 4.75e-07,
    "output": "0.000475",
    "timestamp": 1760528853.8107858,
    "vertices": 60,
    "time_bound": 9
  },
  {
    "solver": "ontime",
    "game": "test083",
    "status": "success",
    "time": 0.0126495361328125,
    "output": "W_9 = {\"v46\", \"v56\", \"v39\", \"v57\", \"v52\", \"v22\"}\nW_0 = {}",
    "timestamp": 1760528853.8235238,
    "vertices": 60,
    "time_bound": 9
  },
  {
    "solver": "temporis",
    "game": "test084",
    "status": "success",
    "time": 3.9800000000000004e-07,
    "output": "0.000398",
    "timestamp": 1760528853.826706,
    "vertices": 60,
    "time_bound": 9
  },
  {
    "solver": "ontime",
    "game": "test084",
    "status": "success",
    "time": 0.009480953216552734,
    "output": "W_9 = {\"v48\", \"v58\", \"v36\", \"v43\", \"v13\", \"v26\", \"v52\", \"v19\"}\nW_0 = {\"v43\"}",
    "timestamp": 1760528853.8363028,
    "vertices": 60,
    "time_bound": 9
  },
  {
    "solver": "temporis",
    "game": "test085",
    "status": "success",
    "time": 3.96e-07,
    "output": "0.000396",
    "timestamp": 1760528853.8398292,
    "vertices": 60,
    "time_bound": 9
  },
  {
    "solver": "ontime",
    "game": "test085",
    "status": "success",
    "time": 0.01145029067993164,
    "output": "W_9 = {\"v8\", \"v57\", \"v53\", \"v34\", \"v30\", \"v40\", \"v2\"}\nW_0 = {\"v41\", \"v6\", \"v34\"}",
    "timestamp": 1760528853.8513935,
    "vertices": 60,
    "time_bound": 9
  },
  {
    "solver": "temporis",
    "game": "test086",
    "status": "success",
    "time": 3.2600000000000003e-07,
    "output": "0.000326",
    "timestamp": 1760528853.8547037,
    "vertices": 60,
    "time_bound": 6
  },
  {
    "solver": "ontime",
    "game": "test086",
    "status": "success",
    "time": 0.010844707489013672,
    "output": "W_6 = {\"v41\", \"v11\", \"v1\", \"v36\", \"v6\", \"v23\", \"v10\", \"v27\", \"v51\", \"v38\", \"v31\"}\nW_0 = {}",
    "timestamp": 1760528853.8656502,
    "vertices": 60,
    "time_bound": 6
  },
  {
    "solver": "temporis",
    "game": "test087",
    "status": "success",
    "time": 4.82e-07,
    "output": "0.000482",
    "timestamp": 1760528853.869622,
    "vertices": 60,
    "time_bound": 11
  },
  {
    "solver": "ontime",
    "game": "test087",
    "status": "success",
    "time": 0.013833045959472656,
    "output": "W_11 = {\"v42\", \"v8\", \"v27\", \"v40\", \"v2\", \"v0\", \"v48\", \"v10\", \"v35\"}\nW_0 = {}",
    "timestamp": 1760528853.8835843,
    "vertices": 60,
    "time_bound": 11
  },
  {
    "solver": "temporis",
    "game": "test088",
    "status": "success",
    "time": 2.34e-07,
    "output": "0.000234",
    "timestamp": 1760528853.8864806,
    "vertices": 60,
    "time_bound": 11
  },
  {
    "solver": "ontime",
    "game": "test088",
    "status": "success",
    "time": 0.008170127868652344,
    "output": "W_11 = {\"v32\", \"v41\", \"v57\", \"v31\", \"v27\", \"v6\", \"v12\"}\nW_0 = {}",
    "timestamp": 1760528853.8947594,
    "vertices": 60,
    "time_bound": 11
  },
  {
    "solver": "temporis",
    "game": "test089",
    "status": "success",
    "time": 2.79e-07,
    "output": "0.000279",
    "timestamp": 1760528853.8977263,
    "vertices": 60,
    "time_bound": 10
  },
  {
    "solver": "ontime",
    "game": "test089",
    "status": "success",
    "time": 0.00817251205444336,
    "output": "W_10 = {\"v1\", \"v21\", \"v58\", \"v13\", \"v28\", \"v26\", \"v35\", \"v43\", \"v14\"}\nW_0 = {\"v49\"}",
    "timestamp": 1760528853.905984,
    "vertices": 60,
    "time_bound": 10
  },
  {
    "solver": "temporis",
    "game": "test090",
    "status": "success",
    "time": 2.45e-07,
    "output": "0.000245",
    "timestamp": 1760528853.9088893,
    "vertices": 60,
    "time_bound": 10
  },
  {
    "solver": "ontime",
    "game": "test090",
    "status": "success",
    "time": 0.008284807205200195,
    "output": "W_10 = {\"v38\", \"v51\", \"v33\", \"v27\", \"v34\", \"v9\", \"v57\", \"v22\", \"v24\", \"v0\"}\nW_0 = {\"v38\", \"v24\"}",
    "timestamp": 1760528853.9172728,
    "vertices": 60,
    "time_bound": 10
  },
  {
    "solver": "temporis",
    "game": "test091",
    "status": "success",
    "time": 6.44e-07,
    "output": "0.000644",
    "timestamp": 1760528853.9213288,
    "vertices": 70,
    "time_bound": 8
  },
  {
    "solver": "ontime",
    "game": "test091",
    "status": "success",
    "time": 0.01419210433959961,
    "output": "W_8 = {\"v53\", \"v69\", \"v41\", \"v42\", \"v52\", \"v16\", \"v14\", \"v49\", \"v9\"}\nW_0 = {\"v69\", \"v56\", \"v24\"}",
    "timestamp": 1760528853.9356449,
    "vertices": 70,
    "time_bound": 8
  },
  {
    "solver": "temporis",
    "game": "test092",
    "status": "success",
    "time": 4.04e-07,
    "output": "0.000404",
    "timestamp": 1760528853.9391327,
    "vertices": 70,
    "time_bound": 12
  },
  {
    "solver": "ontime",
    "game": "test092",
    "status": "success",
    "time": 0.01124119758605957,
    "output": "W_12 = {\"v50\", \"v46\", \"v33\", \"v40\", \"v17\", \"v60\", \"v57\", \"v63\", \"v47\", \"v49\", \"v54\", \"v30\"}\nW_0 = {\"v8\"}",
    "timestamp": 1760528853.950503,
    "vertices": 70,
    "time_bound": 12
  },
  {
    "solver": "temporis",
    "game": "test093",
    "status": "success",
    "time": 4.08e-07,
    "output": "0.000408",
    "timestamp": 1760528853.9541626,
    "vertices": 70,
    "time_bound": 8
  },
  {
    "solver": "ontime",
    "game": "test093",
    "status": "success",
    "time": 0.01277780532836914,
    "output": "W_8 = {\"v67\", \"v37\", \"v47\", \"v25\", \"v13\", \"v22\", \"v14\", \"v38\", \"v34\", \"v23\", \"v29\"}\nW_0 = {}",
    "timestamp": 1760528853.9670568,
    "vertices": 70,
    "time_bound": 8
  },
  {
    "solver": "temporis",
    "game": "test094",
    "status": "success",
    "time": 2.94e-07,
    "output": "0.000294",
    "timestamp": 1760528853.970106,
    "vertices": 70,
    "time_bound": 7
  },
  {
    "solver": "ontime",
    "game": "test094",
    "status": "success",
    "time": 0.01013803482055664,
    "output": "W_7 = {\"v49\", \"v44\", \"v40\", \"v31\", \"v52\", \"v17\", \"v50\", \"v56\"}\nW_0 = {\"v57\", \"v51\"}",
    "timestamp": 1760528853.9803402,
    "vertices": 70,
    "time_bound": 7
  },
  {
    "solver": "temporis",
    "game": "test095",
    "status": "success",
    "time": 8.24e-07,
    "output": "0.000824",
    "timestamp": 1760528853.9859755,
    "vertices": 70,
    "time_bound": 7
  },
  {
    "solver": "ontime",
    "game": "test095",
    "status": "success",
    "time": 0.017800331115722656,
    "output": "W_7 = {\"v65\", \"v13\", \"v54\", \"v24\", \"v9\", \"v48\", \"v42\", \"v56\", \"v44\", \"v30\"}\nW_0 = {\"v6\", \"v12\", \"v64\", \"v68\", \"v23\"}",
    "timestamp": 1760528854.003908,
    "vertices": 70,
    "time_bound": 7
  },
  {
    "solver": "temporis",
    "game": "test096",
    "status": "success",
    "time": 4.45e-07,
    "output": "0.000445",
    "timestamp": 1760528854.0077822,
    "vertices": 70,
    "time_bound": 7
  },
  {
    "solver": "ontime",
    "game": "test096",
    "status": "success",
    "time": 0.01167154312133789,
    "output": "W_7 = {\"v67\", \"v54\", \"v3\", \"v14\", \"v33\", \"v59\", \"v51\", \"v55\", \"v0\", \"v58\"}\nW_0 = {\"v54\", \"v8\", \"v52\", \"v63\", \"v6\", \"v27\", \"v69\", \"v29\", \"v3\", \"v46\", \"v68\"}",
    "timestamp": 1760528854.0196145,
    "vertices": 70,
    "time_bound": 7
  },
  {
    "solver": "temporis",
    "game": "test097",
    "status": "success",
    "time": 7.36e-07,
    "output": "0.000736",
    "timestamp": 1760528854.0239892,
    "vertices": 70,
    "time_bound": 10
  },
  {
    "solver": "ontime",
    "game": "test097",
    "status": "success",
    "time": 0.01487278938293457,
    "output": "W_10 = {\"v12\", \"v65\", \"v26\", \"v9\", \"v6\", \"v54\", \"v23\", \"v39\", \"v29\", \"v18\", \"v11\"}\nW_0 = {\"v20\", \"v51\", \"v12\", \"v13\", \"v11\", \"v37\"}",
    "timestamp": 1760528854.0390232,
    "vertices": 70,
    "time_bound": 10
  },
  {
    "solver": "temporis",
    "game": "test098",
    "status": "success",
    "time": 7.57e-07,
    "output": "0.000757",
    "timestamp": 1760528854.0436747,
    "vertices": 70,
    "time_bound": 12
  },
  {
    "solver": "ontime",
    "game": "test098",
    "status": "success",
    "time": 0.023258447647094727,
    "output": "W_12 = {\"v29\", \"v35\", \"v10\", \"v17\", \"v11\", \"v65\", \"v47\", \"v43\", \"v8\", \"v6\", \"v41\", \"v0\", \"v32\"}\nW_0 = {}",
    "timestamp": 1760528854.0671015,
    "vertices": 70,
    "time_bound": 12
  },
  {
    "solver": "temporis",
    "game": "test099",
    "status": "success",
    "time": 1.167e-06,
    "output": "0.001167",
    "timestamp": 1760528854.0761082,
    "vertices": 70,
    "time_bound": 13
  },
  {
    "solver": "ontime",
    "game": "test099",
    "status": "success",
    "time": 0.03497815132141113,
    "output": "W_13 = {\"v48\", \"v0\", \"v20\", \"v14\", \"v10\", \"v43\", \"v28\", \"v18\", \"v1\", \"v30\", \"v5\", \"v11\"}\nW_0 = {}",
    "timestamp": 1760528854.1112976,
    "vertices": 70,
    "time_bound": 13
  },
  {
    "solver": "temporis",
    "game": "test100",
    "status": "success",
    "time": 1.142e-06,
    "output": "0.001142",
    "timestamp": 1760528854.1215897,
    "vertices": 70,
    "time_bound": 10
  },
  {
    "solver": "ontime",
    "game": "test100",
    "status": "success",
    "time": 0.026973485946655273,
    "output": "W_10 = {\"v41\", \"v58\", \"v36\", \"v11\", \"v17\", \"v7\", \"v32\", \"v61\", \"v51\", \"v3\", \"v15\"}\nW_0 = {\"v9\", \"v65\", \"v68\", \"v34\", \"v0\", \"v32\", \"v41\", \"v44\", \"v38\", \"v48\", \"v59\", \"v29\", \"v42\", \"v54\"}",
    "timestamp": 1760528854.1487734,
    "vertices": 70,
    "time_bound": 10
  },
  {
    "solver": "temporis",
    "game": "test101",
    "status": "success",
    "time": 8.930000000000001e-07,
    "output": "0.000893",
    "timestamp": 1760528854.1545951,
    "vertices": 70,
    "time_bound": 14
  },
  {
    "solver": "ontime",
    "game": "test101",
    "status": "success",
    "time": 0.017268896102905273,
    "output": "W_14 = {\"v21\", \"v18\", \"v11\", \"v33\", \"v68\", \"v19\", \"v54\", \"v45\", \"v31\", \"v14\", \"v0\", \"v64\"}\nW_0 = {}",
    "timestamp": 1760528854.173846,
    "vertices": 70,
    "time_bound": 14
  },
  {
    "solver": "temporis",
    "game": "test102",
    "status": "success",
    "time": 3.57e-07,
    "output": "0.000357",
    "timestamp": 1760528854.1774986,
    "vertices": 70,
    "time_bound": 13
  },
  {
    "solver": "ontime",
    "game": "test102",
    "status": "success",
    "time": 0.011058568954467773,
    "output": "W_13 = {\"v1\", \"v16\", \"v55\", \"v24\", \"v39\", \"v51\", \"v69\"}\nW_0 = {}",
    "timestamp": 1760528854.1887045,
    "vertices": 70,
    "time_bound": 13
  },
  {
    "solver": "temporis",
    "game": "test103",
    "status": "success",
    "time": 3.21e-07,
    "output": "0.000321",
    "timestamp": 1760528854.19217,
    "vertices": 70,
    "time_bound": 9
  },
  {
    "solver": "ontime",
    "game": "test103",
    "status": "success",
    "time": 0.009955644607543945,
    "output": "W_9 = {\"v3\", \"v61\", \"v52\", \"v27\", \"v66\", \"v35\", \"v37\", \"v31\", \"v24\", \"v56\", \"v12\", \"v10\", \"v34\"}\nW_0 = {\"v26\"}",
    "timestamp": 1760528854.2022655,
    "vertices": 70,
    "time_bound": 9
  },
  {
    "solver": "temporis",
    "game": "test104",
    "status": "success",
    "time": 5.72e-07,
    "output": "0.000572",
    "timestamp": 1760528854.206248,
    "vertices": 70,
    "time_bound": 8
  },
  {
    "solver": "ontime",
    "game": "test104",
    "status": "success",
    "time": 0.013000011444091797,
    "output": "W_8 = {\"v48\", \"v61\", \"v55\", \"v9\", \"v15\", \"v50\", \"v38\", \"v2\", \"v49\", \"v33\", \"v57\", \"v58\"}\nW_0 = {\"v59\"}",
    "timestamp": 1760528854.2194126,
    "vertices": 70,
    "time_bound": 8
  },
  {
    "solver": "temporis",
    "game": "test105",
    "status": "success",
    "time": 5.53e-07,
    "output": "0.000553",
    "timestamp": 1760528854.2236197,
    "vertices": 70,
    "time_bound": 12
  },
  {
    "solver": "ontime",
    "game": "test105",
    "status": "success",
    "time": 0.014363765716552734,
    "output": "W_12 = {\"v49\", \"v12\", \"v42\", \"v54\", \"v64\", \"v13\", \"v16\"}\nW_0 = {}",
    "timestamp": 1760528854.2381375,
    "vertices": 70,
    "time_bound": 12
  },
  {
    "solver": "temporis",
    "game": "test106",
    "status": "success",
    "time": 4.11e-07,
    "output": "0.000411",
    "timestamp": 1760528854.2420025,
    "vertices": 80,
    "time_bound": 10
  },
  {
    "solver": "ontime",
    "game": "test106",
    "status": "success",
    "time": 0.012345552444458008,
    "output": "W_10 = {\"v61\", \"v2\", \"v23\", \"v26\", \"v72\", \"v35\", \"v8\", \"v73\", \"v36\", \"v24\", \"v1\", \"v16\"}\nW_0 = {}",
    "timestamp": 1760528854.254493,
    "vertices": 80,
    "time_bound": 10
  },
  {
    "solver": "temporis",
    "game": "test107",
    "status": "success",
    "time": 5.4e-07,
    "output": "0.000540",
    "timestamp": 1760528854.2590168,
    "vertices": 80,
    "time_bound": 15
  },
  {
    "solver": "ontime",
    "game": "test107",
    "status": "success",
    "time": 0.014877796173095703,
    "output": "W_15 = {\"v4\", \"v56\", \"v20\", \"v37\", \"v53\", \"v45\", \"v21\", \"v67\", \"v61\", \"v43\", \"v77\", \"v17\"}\nW_0 = {}",
    "timestamp": 1760528854.274042,
    "vertices": 80,
    "time_bound": 15
  },
  {
    "solver": "temporis",
    "game": "test108",
    "status": "success",
    "time": 4.84e-07,
    "output": "0.000484",
    "timestamp": 1760528854.277819,
    "vertices": 80,
    "time_bound": 15
  },
  {
    "solver": "ontime",
    "game": "test108",
    "status": "success",
    "time": 0.012457609176635742,
    "output": "W_15 = {\"v43\", \"v70\", \"v78\", \"v79\", \"v28\", \"v67\", \"v50\", \"v16\", \"v56\", \"v60\", \"v62\", \"v55\", \"v45\", \"v8\", \"v32\"}\nW_0 = {\"v41\", \"v77\", \"v23\", \"v17\", \"v14\", \"v5\", \"v7\", \"v45\", \"v16\"}",
    "timestamp": 1760528854.2904081,
    "vertices": 80,
    "time_bound": 15
  },
  {
    "solver": "temporis",
    "game": "test109",
    "status": "success",
    "time": 7.380000000000001e-07,
    "output": "0.000738",
    "timestamp": 1760528854.295287,
    "vertices": 80,
    "time_bound": 15
  },
  {
    "solver": "ontime",
    "game": "test109",
    "status": "success",
    "time": 0.01784062385559082,
    "output": "W_15 = {\"v13\", \"v8\", \"v20\", \"v32\", \"v54\", \"v3\", \"v24\", \"v11\"}\nW_0 = {\"v13\", \"v67\", \"v14\", \"v73\"}",
    "timestamp": 1760528854.3132615,
    "vertices": 80,
    "time_bound": 15
  },
  {
    "solver": "temporis",
    "game": "test110",
    "status": "success",
    "time": 4.04e-07,
    "output": "0.000404",
    "timestamp": 1760528854.3167064,
    "vertices": 80,
    "time_bound": 9
  },
  {
    "solver": "ontime",
    "game": "test110",
    "status": "success",
    "time": 0.012166976928710938,
    "output": "W_9 = {\"v44\", \"v10\", \"v15\", \"v49\", \"v72\", \"v23\", \"v54\", \"v32\", \"v77\", \"v30\", \"v17\", \"v0\", \"v73\"}\nW_0 = {}",
    "timestamp": 1760528854.3289804,
    "vertices": 80,
    "time_bound": 9
  },
  {
    "solver": "temporis",
    "game": "test111",
    "status": "success",
    "time": 7.17e-07,
    "output": "0.000717",
    "timestamp": 1760528854.3333206,
    "vertices": 80,
    "time_bound": 12
  },
  {
    "solver": "ontime",
    "game": "test111",
    "status": "success",
    "time": 0.016504526138305664,
    "output": "W_12 = {\"v69\", \"v54\", \"v4\", \"v29\", \"v63\", \"v31\", \"v44\", \"v58\", \"v40\", \"v53\", \"v9\", \"v60\", \"v36\"}\nW_0 = {\"v69\"}",
    "timestamp": 1760528854.3499894,
    "vertices": 80,
    "time_bound": 12
  },
  {
    "solver": "temporis",
    "game": "test112",
    "status": "success",
    "time": 1.131e-06,
    "output": "0.001131",
    "timestamp": 1760528854.35566,
    "vertices": 80,
    "time_bound": 15
  },
  {
    "solver": "ontime",
    "game": "test112",
    "status": "success",
    "time": 0.016937255859375,
    "output": "W_15 = {\"v13\", \"v19\", \"v56\", \"v55\", \"v59\", \"v27\", \"v73\", \"v57\"}\nW_0 = {\"v46\", \"v50\"}",
    "timestamp": 1760528854.3727834,
    "vertices": 80,
    "time_bound": 15
  },
  {
    "solver": "temporis",
    "game": "test113",
    "status": "success",
    "time": 5.62e-07,
    "output": "0.000562",
    "timestamp": 1760528854.3773887,
    "vertices": 80,
    "time_bound": 11
  },
  {
    "solver": "ontime",
    "game": "test113",
    "status": "success",
    "time": 0.01771688461303711,
    "output": "W_11 = {\"v46\", \"v25\", \"v20\", \"v40\", \"v53\", \"v75\", \"v11\", \"v13\", \"v64\", \"v31\", \"v26\", \"v61\", \"v60\", \"v69\"}\nW_0 = {}",
    "timestamp": 1760528854.395246,
    "vertices": 80,
    "time_bound": 11
  },
  {
    "solver": "temporis",
    "game": "test114",
    "status": "success",
    "time": 5.38e-07,
    "output": "0.000538",
    "timestamp": 1760528854.399409,
    "vertices": 80,
    "time_bound": 8
  },
  {
    "solver": "ontime",
    "game": "test114",
    "status": "success",
    "time": 0.01918768882751465,
    "output": "W_8 = {\"v64\", \"v59\", \"v76\", \"v47\", \"v36\", \"v5\", \"v14\", \"v53\", \"v32\", \"v28\", \"v18\", \"v11\", \"v73\"}\nW_0 = {}",
    "timestamp": 1760528854.4187326,
    "vertices": 80,
    "time_bound": 8
  },
  {
    "solver": "temporis",
    "game": "test115",
    "status": "success",
    "time": 3.83e-07,
    "output": "0.000383",
    "timestamp": 1760528854.4221227,
    "vertices": 80,
    "time_bound": 12
  },
  {
    "solver": "ontime",
    "game": "test115",
    "status": "success",
    "time": 0.010361194610595703,
    "output": "W_12 = {\"v26\", \"v44\", \"v11\", \"v22\", \"v77\", \"v12\", \"v9\", \"v54\", \"v36\", \"v34\", \"v78\"}\nW_0 = {}",
    "timestamp": 1760528854.432654,
    "vertices": 80,
    "time_bound": 12
  },
  {
    "solver": "temporis",
    "game": "test116",
    "status": "success",
    "time": 7.06e-07,
    "output": "0.000706",
    "timestamp": 1760528854.4368646,
    "vertices": 80,
    "time_bound": 10
  },
  {
    "solver": "ontime",
    "game": "test116",
    "status": "success",
    "time": 0.015141487121582031,
    "output": "W_10 = {\"v10\", \"v46\", \"v36\", \"v64\", \"v69\", \"v75\", \"v39\", \"v32\", \"v53\", \"v23\"}\nW_0 = {}",
    "timestamp": 1760528854.4521315,
    "vertices": 80,
    "time_bound": 10
  },
  {
    "solver": "temporis",
    "game": "test117",
    "status": "success",
    "time": 9.349999999999999e-07,
    "output": "0.000935",
    "timestamp": 1760528854.45756,
    "vertices": 80,
    "time_bound": 12
  },
  {
    "solver": "ontime",
    "game": "test117",
    "status": "success",
    "time": 0.017709016799926758,
    "output": "W_12 = {\"v56\", \"v79\", \"v48\", \"v18\", \"v14\", \"v52\", \"v32\", \"v0\", \"v37\", \"v64\", \"v77\", \"v8\", \"v5\", \"v72\", \"v19\"}\nW_0 = {}",
    "timestamp": 1760528854.475434,
    "vertices": 80,
    "time_bound": 12
  },
  {
    "solver": "temporis",
    "game": "test118",
    "status": "success",
    "time": 7.799999999999999e-07,
    "output": "0.000780",
    "timestamp": 1760528854.4806416,
    "vertices": 80,
    "time_bound": 16
  },
  {
    "solver": "ontime",
    "game": "test118",
    "status": "success",
    "time": 0.025021076202392578,
    "output": "W_16 = {\"v10\", \"v71\", \"v45\", \"v43\", \"v68\", \"v33\", \"v78\", \"v20\", \"v24\", \"v65\", \"v1\", \"v63\", \"v69\", \"v47\", \"v52\"}\nW_0 = {\"v72\", \"v75\", \"v19\"}",
    "timestamp": 1760528854.5057962,
    "vertices": 80,
    "time_bound": 16
  },
  {
    "solver": "temporis",
    "game": "test119",
    "status": "success",
    "time": 7.33e-07,
    "output": "0.000733",
    "timestamp": 1760528854.5109384,
    "vertices": 80,
    "time_bound": 16
  },
  {
    "solver": "ontime",
    "game": "test119",
    "status": "success",
    "time": 0.017873287200927734,
    "output": "W_16 = {\"v70\", \"v69\", \"v0\", \"v67\", \"v8\", \"v49\", \"v74\", \"v3\", \"v78\", \"v65\", \"v11\", \"v66\"}\nW_0 = {\"v34\", \"v44\", \"v20\", \"v41\", \"v7\", \"v15\", \"v45\", \"v39\", \"v6\", \"v62\", \"v48\"}",
    "timestamp": 1760528854.528938,
    "vertices": 80,
    "time_bound": 16
  },
  {
    "solver": "temporis",
    "game": "test120",
    "status": "success",
    "time": 5.469999999999999e-07,
    "output": "0.000547",
    "timestamp": 1760528854.5332315,
    "vertices": 80,
    "time_bound": 9
  },
  {
    "solver": "ontime",
    "game": "test120",
    "status": "success",
    "time": 0.01801776885986328,
    "output": "W_9 = {\"v57\", \"v43\", \"v51\", \"v28\", \"v10\", \"v60\", \"v77\", \"v45\", \"v34\", \"v47\", \"v79\", \"v64\", \"v53\", \"v61\", \"v31\"}\nW_0 = {\"v39\"}",
    "timestamp": 1760528854.5513928,
    "vertices": 80,
    "time_bound": 9
  },
  {
    "solver": "temporis",
    "game": "test121",
    "status": "success",
    "time": 1.25e-06,
    "output": "0.001250",
    "timestamp": 1760528854.5576713,
    "vertices": 90,
    "time_bound": 16
  },
  {
    "solver": "ontime",
    "game": "test121",
    "status": "success",
    "time": 0.021267414093017578,
    "output": "W_16 = {\"v57\", \"v42\", \"v74\", \"v26\", \"v68\", \"v12\", \"v81\", \"v6\", \"v20\", \"v70\", \"v66\", \"v64\", \"v0\", \"v45\"}\nW_0 = {}",
    "timestamp": 1760528854.5791278,
    "vertices": 90,
    "time_bound": 16
  },
  {
    "solver": "temporis",
    "game": "test122",
    "status": "success",
    "time": 7.75e-07,
    "output": "0.000775",
    "timestamp": 1760528854.5839076,
    "vertices": 90,
    "time_bound": 10
  },
  {
    "solver": "ontime",
    "game": "test122",
    "status": "success",
    "time": 0.018596410751342773,
    "output": "W_10 = {\"v75\", \"v79\", \"v37\", \"v58\", \"v24\", \"v6\", \"v48\", \"v33\", \"v66\", \"v0\", \"v42\", \"v69\"}\nW_0 = {}",
    "timestamp": 1760528854.6026704,
    "vertices": 90,
    "time_bound": 10
  },
  {
    "solver": "temporis",
    "game": "test123",
    "status": "success",
    "time": 1.143e-06,
    "output": "0.001143",
    "timestamp": 1760528854.6080081,
    "vertices": 90,
    "time_bound": 16
  },
  {
    "solver": "ontime",
    "game": "test123",
    "status": "success",
    "time": 0.016956806182861328,
    "output": "W_16 = {\"v60\", \"v79\", \"v2\", \"v54\", \"v29\", \"v84\", \"v63\", \"v24\", \"v66\", \"v34\"}\nW_0 = {\"v21\", \"v49\", \"v33\", \"v3\", \"v4\", \"v26\", \"v45\", \"v82\", \"v50\", \"v19\", \"v9\", \"v83\", \"v52\", \"v71\", \"v15\", \"v0\", \"v42\", \"v57\", \"v8\", \"v48\"}",
    "timestamp": 1760528854.6251426,
    "vertices": 90,
    "time_bound": 16
  },
  {
    "solver": "temporis",
    "game": "test124",
    "status": "success",
    "time": 4.93e-07,
    "output": "0.000493",
    "timestamp": 1760528854.6289666,
    "vertices": 90,
    "time_bound": 17
  },
  {
    "solver": "ontime",
    "game": "test124",
    "status": "success",
    "time": 0.013624191284179688,
    "output": "W_17 = {\"v3\", \"v76\", \"v37\", \"v24\", \"v40\", \"v79\", \"v8\", \"v19\", \"v7\", \"v64\"}\nW_0 = {}",
    "timestamp": 1760528854.6427093,
    "vertices": 90,
    "time_bound": 17
  },
  {
    "solver": "temporis",
    "game": "test125",
    "status": "success",
    "time": 4.94e-07,
    "output": "0.000494",
    "timestamp": 1760528854.6466293,
    "vertices": 90,
    "time_bound": 9
  },
  {
    "solver": "ontime",
    "game": "test125",
    "status": "success",
    "time": 0.013715744018554688,
    "output": "W_9 = {\"v5\", \"v45\", \"v3\", \"v13\", \"v64\", \"v14\", \"v40\", \"v36\", \"v56\", \"v63\", \"v81\", \"v84\", \"v6\", \"v78\"}\nW_0 = {}",
    "timestamp": 1760528854.6604974,
    "vertices": 90,
    "time_bound": 9
  },
  {
    "solver": "temporis",
    "game": "test126",
    "status": "success",
    "time": 6.83e-07,
    "output": "0.000683",
    "timestamp": 1760528854.6651423,
    "vertices": 90,
    "time_bound": 10
  },
  {
    "solver": "ontime",
    "game": "test126",
    "status": "success",
    "time": 0.018363475799560547,
    "output": "W_10 = {\"v22\", \"v50\", \"v37\", \"v41\", \"v25\", \"v8\", \"v28\", \"v51\", \"v13\", \"v75\", \"v43\", \"v0\", \"v89\", \"v54\", \"v69\"}\nW_0 = {\"v78\", \"v2\", \"v77\", \"v42\", \"v60\", \"v17\", \"v89\", \"v11\", \"v36\", \"v41\", \"v19\"}",
    "timestamp": 1760528854.6836839,
    "vertices": 90,
    "time_bound": 10
  },
  {
    "solver": "temporis",
    "game": "test127",
    "status": "success",
    "time": 4.22e-07,
    "output": "0.000422",
    "timestamp": 1760528854.6872776,
    "vertices": 90,
    "time_bound": 18
  },
  {
    "solver": "ontime",
    "game": "test127",
    "status": "success",
    "time": 0.012535810470581055,
    "output": "W_18 = {\"v59\", \"v80\", \"v33\", \"v41\", \"v40\", \"v37\", \"v12\", \"v75\", \"v65\", \"v11\", \"v85\", \"v60\"}\nW_0 = {\"v20\", \"v48\"}",
    "timestamp": 1760528854.6999595,
    "vertices": 90,
    "time_bound": 18
  },
  {
    "solver": "temporis",
    "game": "test128",
    "status": "success",
    "time": 7.699999999999999e-07,
    "output": "0.000770",
    "timestamp": 1760528854.704779,
    "vertices": 90,
    "time_bound": 17
  },
  {
    "solver": "ontime",
    "game": "test128",
    "status": "success",
    "time": 0.017918825149536133,
    "output": "W_17 = {\"v83\", \"v46\", \"v35\", \"v37\", \"v20\", \"v56\", \"v64\", \"v4\", \"v74\", \"v84\", \"v73\", \"v22\", \"v49\", \"v60\", \"v79\", \"v72\"}\nW_0 = {\"v20\", \"v13\"}",
    "timestamp": 1760528854.7228234,
    "vertices": 90,
    "time_bound": 17
  },
  {
    "solver": "temporis",
    "game": "test129",
    "status": "success",
    "time": 4.85e-07,
    "output": "0.000485",
    "timestamp": 1760528854.7269714,
    "vertices": 90,
    "time_bound": 12
  },
  {
    "solver": "ontime",
    "game": "test129",
    "status": "success",
    "time": 0.014053106307983398,
    "output": "W_12 = {\"v28\", \"v77\", \"v39\", \"v87\", \"v74\", \"v41\", \"v29\", \"v8\", \"v70\", \"v58\", \"v60\", \"v63\"}\nW_0 = {}",
    "timestamp": 1760528854.7411664,
    "vertices": 90,
    "time_bound": 12
  },
  {
    "solver": "temporis",
    "game": "test130",
    "status": "success",
    "time": 6.64e-07,
    "output": "0.000664",
    "timestamp": 1760528854.7456646,
    "vertices": 90,
    "time_bound": 15
  },
  {
    "solver": "ontime",
    "game": "test130",
    "status": "success",
    "time": 0.01674056053161621,
    "output": "W_15 = {\"v68\", \"v88\", \"v20\", \"v55\", \"v40\", \"v56\", \"v27\", \"v64\", \"v54\"}\nW_0 = {}",
    "timestamp": 1760528854.7625535,
    "vertices": 90,
    "time_bound": 15
  },
  {
    "solver": "temporis",
    "game": "test131",
    "status": "success",
    "time": 4.1599999999999997e-07,
    "output": "0.000416",
    "timestamp": 1760528854.7660575,
    "vertices": 90,
    "time_bound": 13
  },
  {
    "solver": "ontime",
    "game": "test131",
    "status": "success",
    "time": 0.012636661529541016,
    "output": "W_13 = {\"v73\", \"v75\", \"v43\", \"v31\", \"v33\", \"v62\", \"v49\", \"v15\", \"v7\", \"v64\", \"v56\", \"v37\"}\nW_0 = {}",
    "timestamp": 1760528854.7788286,
    "vertices": 90,
    "time_bound": 13
  },
  {
    "solver": "temporis",
    "game": "test132",
    "status": "success",
    "time": 6.79e-07,
    "output": "0.000679",
    "timestamp": 1760528854.7835367,
    "vertices": 90,
    "time_bound": 17
  },
  {
    "solver": "ontime",
    "game": "test132",
    "status": "success",
    "time": 0.018026113510131836,
    "output": "W_17 = {\"v51\", \"v86\", \"v73\", \"v10\", \"v89\", \"v17\", \"v80\", \"v35\", \"v47\", \"v67\", \"v36\", \"v30\", \"v58\"}\nW_0 = {}",
    "timestamp": 1760528854.801783,
    "vertices": 90,
    "time_bound": 17
  },
  {
    "solver": "temporis",
    "game": "test133",
    "status": "success",
    "time": 7.95e-07,
    "output": "0.000795",
    "timestamp": 1760528854.8069117,
    "vertices": 90,
    "time_bound": 12
  },
  {
    "solver": "ontime",
    "game": "test133",
    "status": "success",
    "time": 0.016364336013793945,
    "output": "W_12 = {\"v46\", \"v41\", \"v43\", \"v68\", \"v55\", \"v33\", \"v60\", \"v84\", \"v4\", \"v37\", \"v10\", \"v69\", \"v5\", \"v49\", \"v20\"}\nW_0 = {}",
    "timestamp": 1760528854.8234313,
    "vertices": 90,
    "time_bound": 12
  },
  {
    "solver": "temporis",
    "game": "test134",
    "status": "success",
    "time": 4.01e-07,
    "output": "0.000401",
    "timestamp": 1760528854.8269448,
    "vertices": 90,
    "time_bound": 17
  },
  {
    "solver": "ontime",
    "game": "test134",
    "status": "success",
    "time": 0.012787103652954102,
    "output": "W_17 = {\"v33\", \"v27\", \"v62\", \"v39\", \"v1\", \"v89\", \"v14\", \"v24\", \"v0\", \"v65\", \"v2\", \"v57\", \"v34\", \"v12\", \"v56\"}\nW_0 = {}",
    "timestamp": 1760528854.839848,
    "vertices": 90,
    "time_bound": 17
  },
  {
    "solver": "temporis",
    "game": "test135",
    "status": "success",
    "time": 1.032e-06,
    "output": "0.001032",
    "timestamp": 1760528854.8455439,
    "vertices": 90,
    "time_bound": 17
  },
  {
    "solver": "ontime",
    "game": "test135",
    "status": "success",
    "time": 0.01956033706665039,
    "output": "W_17 = {\"v37\", \"v61\", \"v81\", \"v11\", \"v39\", \"v60\", \"v13\", \"v30\", \"v49\"}\nW_0 = {\"v82\", \"v47\", \"v83\", \"v18\", \"v2\", \"v19\"}",
    "timestamp": 1760528854.865272,
    "vertices": 90,
    "time_bound": 17
  },
  {
    "solver": "temporis",
    "game": "test136",
    "status": "success",
    "time": 6.49e-07,
    "output": "0.000649",
    "timestamp": 1760528854.8693435,
    "vertices": 100,
    "time_bound": 13
  },
  {
    "solver": "ontime",
    "game": "test136",
    "status": "success",
    "time": 0.013326406478881836,
    "output": "W_13 = {\"v17\", \"v78\", \"v92\", \"v87\", \"v74\", \"v96\", \"v56\", \"v20\", \"v27\", \"v1\"}\nW_0 = {}",
    "timestamp": 1760528854.8828177,
    "vertices": 100,
    "time_bound": 13
  },
  {
    "solver": "temporis",
    "game": "test137",
    "status": "success",
    "time": 8.57e-07,
    "output": "0.000857",
    "timestamp": 1760528854.8874023,
    "vertices": 100,
    "time_bound": 10
  },
  {
    "solver": "ontime",
    "game": "test137",
    "status": "success",
    "time": 0.015906810760498047,
    "output": "W_10 = {\"v88\", \"v46\", \"v57\", \"v34\", \"v36\", \"v93\", \"v86\", \"v82\", \"v22\", \"v52\", \"v42\", \"v20\", \"v24\", \"v35\"}\nW_0 = {}",
    "timestamp": 1760528854.903461,
    "vertices": 100,
    "time_bound": 10
  },
  {
    "solver": "temporis",
    "game": "test138",
    "status": "success",
    "time": 7.420000000000001e-07,
    "output": "0.000742",
    "timestamp": 1760528854.9078596,
    "vertices": 100,
    "time_bound": 16
  },
  {
    "solver": "ontime",
    "game": "test138",
    "status": "success",
    "time": 0.014066219329833984,
    "output": "W_16 = {\"v69\", \"v1\", \"v80\", \"v73\", \"v21\", \"v57\", \"v31\", \"v99\", \"v87\", \"v86\", \"v40\", \"v23\", \"v46\", \"v60\", \"v72\", \"v34\", \"v36\", \"v47\"}\nW_0 = {}",
    "timestamp": 1760528854.9220548,
    "vertices": 100,
    "time_bound": 16
  },
  {
    "solver": "temporis",
    "game": "test139",
    "status": "success",
    "time": 6.210000000000001e-07,
    "output": "0.000621",
    "timestamp": 1760528854.9264953,
    "vertices": 100,
    "time_bound": 17
  },
  {
    "solver": "ontime",
    "game": "test139",
    "status": "success",
    "time": 0.019187211990356445,
    "output": "W_17 = {\"v79\", \"v28\", \"v58\", \"v85\", \"v89\", \"v15\", \"v93\", \"v63\", \"v57\", \"v40\", \"v2\"}\nW_0 = {}",
    "timestamp": 1760528854.9458568,
    "vertices": 100,
    "time_bound": 17
  },
  {
    "solver": "temporis",
    "game": "test140",
    "status": "success",
    "time": 9.29e-07,
    "output": "0.000929",
    "timestamp": 1760528854.9511259,
    "vertices": 100,
    "time_bound": 19
  },
  {
    "solver": "ontime",
    "game": "test140",
    "status": "success",
    "time": 0.01897144317626953,
    "output": "W_19 = {\"v52\", \"v72\", \"v55\", \"v6\", \"v94\", \"v34\", \"v48\", \"v15\", \"v63\", \"v32\", \"v47\", \"v38\", \"v64\", \"v5\"}\nW_0 = {}",
    "timestamp": 1760528854.9702837,
    "vertices": 100,
    "time_bound": 19
  },
  {
    "solver": "temporis",
    "game": "test141",
    "status": "success",
    "time": 1.195e-06,
    "output": "0.001195",
    "timestamp": 1760528854.9768162,
    "vertices": 100,
    "time_bound": 14
  },
  {
    "solver": "ontime",
    "game": "test141",
    "status": "success",
    "time": 0.02282547950744629,
    "output": "W_14 = {\"v29\", \"v40\", \"v61\", \"v77\", \"v37\", \"v87\", \"v50\", \"v36\", \"v25\", \"v41\", \"v33\", \"v62\", \"v63\"}\nW_0 = {}",
    "timestamp": 1760528854.999781,
    "vertices": 100,
    "time_bound": 14
  },
  {
    "solver": "temporis",
    "game": "test142",
    "status": "success",
    "time": 6.170000000000001e-07,
    "output": "0.000617",
    "timestamp": 1760528855.0044143,
    "vertices": 100,
    "time_bound": 10
  },
  {
    "solver": "ontime",
    "game": "test142",
    "status": "success",
    "time": 0.017262935638427734,
    "output": "W_10 = {\"v51\", \"v31\", \"v47\", \"v24\", \"v98\", \"v69\", \"v16\", \"v48\", \"v26\", \"v62\", \"v60\", \"v71\", \"v9\", \"v75\", \"v86\", \"v3\"}\nW_0 = {}",
    "timestamp": 1760528855.0218546,
    "vertices": 100,
    "time_bound": 10
  },
  {
    "solver": "temporis",
    "game": "test143",
    "status": "success",
    "time": 4.6700000000000004e-07,
    "output": "0.000467",
    "timestamp": 1760528855.0259004,
    "vertices": 100,
    "time_bound": 14
  },
  {
    "solver": "ontime",
    "game": "test143",
    "status": "success",
    "time": 0.01363062858581543,
    "output": "W_14 = {\"v57\", \"v15\", \"v68\", \"v35\", \"v42\", \"v47\", \"v28\", \"v65\", \"v24\", \"v67\", \"v16\", \"v95\", \"v55\", \"v70\", \"v60\", \"v97\", \"v30\", \"v63\"}\nW_0 = {\"v53\", \"v36\", \"v15\"}",
    "timestamp": 1760528855.0396514,
    "vertices": 100,
    "time_bound": 14
  },
  {
    "solver": "temporis",
    "game": "test144",
    "status": "success",
    "time": 5.389999999999999e-07,
    "output": "0.000539",
    "timestamp": 1760528855.0438335,
    "vertices": 100,
    "time_bound": 18
  },
  {
    "solver": "ontime",
    "game": "test144",
    "status": "success",
    "time": 0.01407170295715332,
    "output": "W_18 = {\"v28\", \"v9\", \"v10\", \"v23\", \"v19\", \"v27\", \"v71\", \"v91\", \"v80\", \"v53\", \"v76\", \"v24\", \"v89\", \"v87\", \"v5\", \"v15\"}\nW_0 = {}",
    "timestamp": 1760528855.058023,
    "vertices": 100,
    "time_bound": 18
  },
  {
    "solver": "temporis",
    "game": "test145",
    "status": "success",
    "time": 1.108e-06,
    "output": "0.001108",
    "timestamp": 1760528855.0635364,
    "vertices": 100,
    "time_bound": 12
  },
  {
    "solver": "ontime",
    "game": "test145",
    "status": "success",
    "time": 0.019064903259277344,
    "output": "W_12 = {\"v23\", \"v43\", \"v60\", \"v27\", \"v33\", \"v83\", \"v51\", \"v4\", \"v93\", \"v75\"}\nW_0 = {\"v3\", \"v76\", \"v93\", \"v2\", \"v42\", \"v16\", \"v52\", \"v43\", \"v62\", \"v46\", \"v19\", \"v38\", \"v4\", \"v15\", \"v21\", \"v41\", \"v10\", \"v75\", \"v33\", \"v77\", \"v67\", \"v82\"}",
    "timestamp": 1760528855.082737,
    "vertices": 100,
    "time_bound": 12
  },
  {
    "solver": "temporis",
    "game": "test146",
    "status": "success",
    "time": 9.84e-07,
    "output": "0.000984",
    "timestamp": 1760528855.0883899,
    "vertices": 100,
    "time_bound": 11
  },
  {
    "solver": "ontime",
    "game": "test146",
    "status": "success",
    "time": 0.022519588470458984,
    "output": "W_11 = {\"v17\", \"v37\", \"v10\", \"v19\", \"v85\", \"v33\", \"v83\", \"v13\", \"v20\", \"v44\", \"v55\", \"v8\", \"v53\", \"v70\", \"v45\", \"v31\", \"v90\"}\nW_0 = {\"v23\", \"v27\", \"v88\", \"v53\", \"v99\", \"v58\", \"v70\", \"v69\", \"v14\", \"v54\", \"v19\", \"v12\", \"v96\", \"v28\", \"v57\"}",
    "timestamp": 1760528855.1110632,
    "vertices": 100,
    "time_bound": 11
  },
  {
    "solver": "temporis",
    "game": "test147",
    "status": "success",
    "time": 8.34e-07,
    "output": "0.000834",
    "timestamp": 1760528855.116377,
    "vertices": 100,
    "time_bound": 18
  },
  {
    "solver": "ontime",
    "game": "test147",
    "status": "success",
    "time": 0.02126002311706543,
    "output": "W_18 = {\"v25\", \"v76\", \"v88\", \"v31\", \"v65\", \"v13\", \"v54\", \"v83\", \"v16\", \"v69\", \"v9\", \"v56\", \"v24\", \"v3\", \"v15\"}\nW_0 = {}",
    "timestamp": 1760528855.13779,
    "vertices": 100,
    "time_bound": 18
  },
  {
    "solver": "temporis",
    "game": "test148",
    "status": "success",
    "time": 6.74e-07,
    "output": "0.000674",
    "timestamp": 1760528855.1421967,
    "vertices": 100,
    "time_bound": 20
  },
  {
    "solver": "ontime",
    "game": "test148",
    "status": "success",
    "time": 0.01636481285095215,
    "output": "W_20 = {\"v93\", \"v90\", \"v97\", \"v50\", \"v73\", \"v31\", \"v71\", \"v70\", \"v45\", \"v86\", \"v42\", \"v7\", \"v57\", \"v81\", \"v80\", \"v34\", \"v14\", \"v4\", \"v5\"}\nW_0 = {\"v35\", \"v95\", \"v73\", \"v25\"}",
    "timestamp": 1760528855.158691,
    "vertices": 100,
    "time_bound": 20
  },
  {
    "solver": "temporis",
    "game": "test149",
    "status": "success",
    "time": 7.94e-07,
    "output": "0.000794",
    "timestamp": 1760528855.1635916,
    "vertices": 100,
    "time_bound": 16
  },
  {
    "solver": "ontime",
    "game": "test149",
    "status": "success",
    "time": 0.017964601516723633,
    "output": "W_16 = {\"v63\", \"v31\", \"v8\", \"v93\", \"v46\", \"v94\", \"v75\", \"v44\", \"v24\", \"v69\", \"v36\", \"v64\", \"v86\", \"v54\", \"v23\", \"v42\"}\nW_0 = {\"v2\", \"v52\", \"v51\", \"v91\", \"v58\", \"v61\", \"v87\", \"v77\", \"v82\", \"v68\", \"v46\", \"v41\", \"v32\", \"v8\", \"v81\", \"v26\", \"v34\"}",
    "timestamp": 1760528855.1816998,
    "vertices": 100,
    "time_bound": 16
  },
  {
    "solver": "temporis",
    "game": "test150",
    "status": "success",
    "time": 8.52e-07,
    "output": "0.000852",
    "timestamp": 1760528855.1867082,
    "vertices": 100,
    "time_bound": 20
  },
  {
    "solver": "ontime",
    "game": "test150",
    "status": "success",
    "time": 0.01836419105529785,
    "output": "W_20 = {\"v58\", \"v99\", \"v82\", \"v67\", \"v39\", \"v56\", \"v22\", \"v52\", \"v11\", \"v78\", \"v86\", \"v74\", \"v28\", \"v68\", \"v33\", \"v77\", \"v73\", \"v17\"}\nW_0 = {}",
    "timestamp": 1760528855.205208,
    "vertices": 100,
    "time_bound": 20
  }
]